sr/__init__.py
sr/resources/toolchain.json
sr/sr.py
sr_filter-0.0.47.dist-info/METADATA
sr_filter-0.0.47.dist-info/WHEEL
sr_filter-0.0.47.dist-info/entry_points.txt
sr_filter-0.0.47.dist-info/RECORD
