Metadata-Version: 2.1
Name: sr-filter
Version: 0.0.47
Summary: Command-line SR toolchain
License: MIT
Author: h1alexbel
Author-email: h1alexbelx@gmail.com
Requires-Python: >=3.10.dev0,<3.13.dev0
Classifier: License :: OSI Approved :: MIT License
Classifier: Programming Language :: Python :: 3
Classifier: Programming Language :: Python :: 3.10
Classifier: Programming Language :: Python :: 3.11
Classifier: Programming Language :: Python :: 3.12
Requires-Dist: loguru (>=0.7.3,<0.8.0)
Requires-Dist: sr-data (==0.0.47)
